amuse_masc/__init__.py
amuse_masc/binaries.py
amuse_masc/make_a_star_cluster.py
amuse_masc/ui.py
amuse_masc-0.2.2.dist-info/LICENSE
amuse_masc-0.2.2.dist-info/METADATA
amuse_masc-0.2.2.dist-info/WHEEL
amuse_masc-0.2.2.dist-info/top_level.txt
amuse_masc-0.2.2.dist-info/RECORD
