Metadata-Version: 2.1
Name: amuse-masc
Version: 0.2.2
Summary: Make a star cluster
Home-page: https://github.com/rieder/masc
Author: Steven Rieder
Author-email: steven@rieder.nl
License: MIT
Platform: UNKNOWN
Classifier: Programming Language :: Python :: 2
Classifier: Programming Language :: Python :: 2.7
Classifier: Programming Language :: Python :: 3
Classifier: License :: OSI Approved :: MIT License
Classifier: Operating System :: OS Independent
Classifier: Development Status :: 4 - Beta
Classifier: Intended Audience :: Science/Research
Requires-Python: >=2.7, !=3.0.*, !=3.1.*, !=3.2.*, <4
